{"cameraMode":{"drawMode":0,"name":"Shaded","section":"Shading Mode"},"sceneLighting":true,"audioPlay":false,"sceneViewState":{"m_AlwaysRefresh":false,"showFog":true,"showSkybox":true,"showFlares":true,"showImageEffects":true,"showParticleSystems":true,"showVisualEffectGraphs":true,"m_FxEnabled":true},"in2DMode":false,"pivot":{"x":242.22152709960938,"y":-0.21705365180969239,"z":126.85906219482422},"rotation":{"x":0.10924450308084488,"y":-0.8793460130691528,"z":0.39427539706230166,"w":0.24364648759365083},"size":2.5361368656158449,"orthographic":false}